{
  "job_id": "job_533ca2fa6867",
  "status": "failed",
  "version": 7,
  "post_url": "https://www.facebook.com/jenniechoo.bangkok/posts/pfbid0jT9SQVdrEbhkGGUTrNiSyETYNQrHBPzdabjLYxvFCjnUquB6waZp5MauoiU7Eb6Gl",
  "post_fingerprint": "3733f1b47e55b2da713eac39c6e4157e8d314f8aa1e1943e0ff3bda76a864b1c",
  "budget_daily_vnd": 123321,
  "campaign_id": null,
  "adset_ids": [],
  "ad_ids": [],
  "creative_ids": [],
  "error": "Meta API loi (400): Error validating access token: Session has expired on Saturday, 16-May-26 06:00:00 PDT. The current time is Saturday, 16-May-26 06:36:12 PDT.",
  "failed_at": "2026-05-16T13:33:41.996916+00:00",
  "updated_at": "2026-05-16T13:33:41.996983+00:00"
}
